dte_adj/__init__.py
dte_adj/base.py
dte_adj/local.py
dte_adj/simple.py
dte_adj/stratified.py
dte_adj/util.py
dte_adj/plot/__init__.py
dte_adj-0.1.8.dist-info/licenses/LICENSE
dte_adj-0.1.8.dist-info/METADATA
dte_adj-0.1.8.dist-info/WHEEL
dte_adj-0.1.8.dist-info/top_level.txt
dte_adj-0.1.8.dist-info/RECORD
