Metadata-Version: 2.4
Name: dte_adj
Version: 0.1.8
Summary: This is a Python library for estimating distributional treatment effects
License-Expression: MIT
Project-URL: homepage, https://github.com/CyberAgentAILab/python-dte-adjustment
Classifier: Programming Language :: Python :: 3
Classifier: Programming Language :: Python :: 3.10
Classifier: Programming Language :: Python :: 3.11
Classifier: Programming Language :: Python :: 3.12
Classifier: Programming Language :: Python :: 3.13
Classifier: Operating System :: OS Independent
Requires-Python: >=3.10
License-File: LICENSE
Requires-Dist: numpy>=1.26
Requires-Dist: matplotlib>=3.7
Requires-Dist: scipy>=1.13.1
Provides-Extra: dev
Requires-Dist: build<1.4.0,>=1.2.2; extra == "dev"
Requires-Dist: ruff<0.14.0,>=0.12.2; extra == "dev"
Requires-Dist: sphinx<8.2.0,>=7.3.7; extra == "dev"
Requires-Dist: scikit-learn<1.8,>=1.5; extra == "dev"
Requires-Dist: pre-commit<4.4.0,>=4.0.1; extra == "dev"
Dynamic: license-file
